hee888/__init__.py
hee888/_init_.py
hee888/app.py
hee888-0.1.2.dist-info/METADATA
hee888-0.1.2.dist-info/WHEEL
hee888-0.1.2.dist-info/entry_points.txt
hee888-0.1.2.dist-info/top_level.txt
hee888-0.1.2.dist-info/RECORD
