Metadata-Version: 2.1
Name: hee888
Version: 0.1.2
Summary: Fast multi-threaded video downloader
Author: Khumi
Requires-Python: >=3.8
Requires-Dist: requests
Requires-Dist: tqdm
Requires-Dist: yt-dlp
